printeq/__init__.py
printeq-0.0.4.data/scripts/printeq
printeq-0.0.4.dist-info/LICENSE
printeq-0.0.4.dist-info/METADATA
printeq-0.0.4.dist-info/WHEEL
printeq-0.0.4.dist-info/top_level.txt
printeq-0.0.4.dist-info/RECORD
