Metadata-Version: 2.1
Name: printeq
Version: 0.0.4
Summary: Render a latex math equation to the terminal.
Home-page: https://github.com/RayCurse/printeq
Author: RayCurse
License: : OSI Approved :: MIT License
Project-URL: Bug Tracker, https://github.com/RayCurse/printeq/issues
Platform: UNKNOWN
Requires-Python: >=3.5
